filelisting/__init__.py
filelisting/__main__.py
filelisting/core/__init__.py
filelisting/tests/__init__.py
filelisting/tests/test_1984.py
filelisting-1.2.6.dist-info/licenses/LICENSE.txt
filelisting-1.2.6.dist-info/METADATA
filelisting-1.2.6.dist-info/WHEEL
filelisting-1.2.6.dist-info/top_level.txt
filelisting-1.2.6.dist-info/RECORD
